reflectorch/__init__.py
reflectorch/paths.py
reflectorch/test_config.py
reflectorch/train.py
reflectorch/train_on_cluster.py
reflectorch/utils.py
reflectorch/data_generation/__init__.py
reflectorch/data_generation/dataset.py
reflectorch/data_generation/likelihoods.py
reflectorch/data_generation/noise.py
reflectorch/data_generation/process_data.py
reflectorch/data_generation/q_generator.py
reflectorch/data_generation/scale_curves.py
reflectorch/data_generation/smearing.py
reflectorch/data_generation/utils.py
reflectorch/data_generation/priors/__init__.py
reflectorch/data_generation/priors/base.py
reflectorch/data_generation/priors/exp_subprior_sampler.py
reflectorch/data_generation/priors/independent_priors.py
reflectorch/data_generation/priors/multilayer_models.py
reflectorch/data_generation/priors/multilayer_structures.py
reflectorch/data_generation/priors/no_constraints.py
reflectorch/data_generation/priors/parametric_models.py
reflectorch/data_generation/priors/parametric_subpriors.py
reflectorch/data_generation/priors/params.py
reflectorch/data_generation/priors/sampler_strategies.py
reflectorch/data_generation/priors/scaler_mixin.py
reflectorch/data_generation/priors/subprior_sampler.py
reflectorch/data_generation/priors/utils.py
reflectorch/data_generation/reflectivity/__init__.py
reflectorch/data_generation/reflectivity/abeles.py
reflectorch/data_generation/reflectivity/kinematical.py
reflectorch/data_generation/reflectivity/memory_eff.py
reflectorch/data_generation/reflectivity/numpy_implementations.py
reflectorch/data_generation/reflectivity/smearing.py
reflectorch/data_generation/reflectivity/smearing_pointwise.py
reflectorch/extensions/__init__.py
reflectorch/extensions/jupyter/__init__.py
reflectorch/extensions/jupyter/api.py
reflectorch/extensions/jupyter/callbacks.py
reflectorch/extensions/jupyter/components.py
reflectorch/extensions/jupyter/custom_select.py
reflectorch/extensions/jupyter/log_widget.py
reflectorch/extensions/jupyter/model_selection.py
reflectorch-1.5.0.dist-info/licenses/LICENSE.txt
reflectorch-1.5.0.dist-info/METADATA
reflectorch-1.5.0.dist-info/WHEEL
reflectorch-1.5.0.dist-info/top_level.txt
reflectorch-1.5.0.dist-info/RECORD
