Metadata-Version: 2.4
Name: reflectorch
Version: 1.5.0
Summary: A Pytorch-based package for the analysis of reflectometry data
Author-email: Vladimir Starostin <vladimir.starostin@uni-tuebingen.de>, Valentin Munteanu <valentin.munteanu@uni-tuebingen.de>
Maintainer-email: Valentin Munteanu <valentin.munteanu@uni-tuebingen.de>, Vladimir Starostin <vladimir.starostin@uni-tuebingen.de>, Alexander Hinderhofer <alexander.hinderhofer@uni-tuebingen.de>
License: MIT
Project-URL: Source, https://github.com/schreiber-lab/reflectorch/
Project-URL: Issues, https://github.com/schreiber-lab/reflectorch/issues
Project-URL: Documentation, https://schreiber-lab.github.io/reflectorch/
Keywords: reflectometry,machine learning
Classifier: Programming Language :: Python :: 3
Classifier: Operating System :: OS Independent
Classifier: Environment :: GPU :: NVIDIA CUDA
Classifier: Development Status :: 4 - Beta
Classifier: Topic :: Scientific/Engineering :: Physics
Classifier: Intended Audience :: Science/Research
Requires-Python: >=3.7
License-File: LICENSE.txt
Requires-Dist: numpy
Requires-Dist: torch>=1.8.1
Requires-Dist: scipy
Requires-Dist: tqdm
Requires-Dist: PyYAML
Requires-Dist: click
Requires-Dist: matplotlib
Requires-Dist: ipywidgets
Requires-Dist: plotly
Requires-Dist: huggingface_hub
Requires-Dist: safetensors
Requires-Dist: tensorboard
Requires-Dist: anywidget
Provides-Extra: tests
Requires-Dist: pytest; extra == "tests"
Requires-Dist: pytest-cov; extra == "tests"
Provides-Extra: docs
Requires-Dist: jupyter-book; extra == "docs"
Requires-Dist: sphinx; extra == "docs"
Provides-Extra: build
Requires-Dist: build; extra == "build"
Requires-Dist: twine; extra == "build"
Dynamic: license-file
